randalyze/__init__.py
randalyze/__main__.py
randalyze/analyzers/__init__.py
randalyze/analyzers/benford.py
randalyze/generators/__init__.py
randalyze/generators/benford.py
randalyze-0.2.1.dist-info/entry_points.txt
randalyze-0.2.1.dist-info/METADATA
randalyze-0.2.1.dist-info/WHEEL
randalyze-0.2.1.dist-info/LICENSE
randalyze-0.2.1.dist-info/RECORD
