Metadata-Version: 2.1
Name: randalyze
Version: 0.2.1
Summary: Create series of random numbers fitting a specified distribution, and then analyze them.
License: Apache-2.0
Keywords: random,generator,Benford,analysis,analyzer
Author: Jason Ross (big-jr)
Author-email: jason@softwarepragmatism.com
Requires-Python: >=3.8,<4.0
Classifier: Development Status :: 4 - Beta
Classifier: Environment :: Console
Classifier: License :: OSI Approved :: Apache Software License
Classifier: Programming Language :: Python :: 3
Classifier: Programming Language :: Python :: 3.8
Classifier: Programming Language :: Python :: 3.9
Classifier: Programming Language :: Python :: 3.10
Classifier: Programming Language :: Python :: 3.11
Project-URL: Original Article, https://www.softwarepragmatism.com/benfords-law
